README.rst
setup.py
PySO8601/__init__.py
PySO8601/__version__.py
PySO8601/datetimestamps.py
PySO8601/durations.py
PySO8601/intervals.py
PySO8601/regexs.py
PySO8601/timezones.py
PySO8601/utility.py
PySO8601.egg-info/PKG-INFO
PySO8601.egg-info/SOURCES.txt
PySO8601.egg-info/dependency_links.txt
PySO8601.egg-info/top_level.txt
specs/__init__.py
specs/basic_specs.py
specs/duration_specs.py
specs/extended_specs.py
specs/interval_specs.py
specs/timezone_specs.py
specs/util_specs.py