Metadata-Version: 1.0
Name: PySO8601
Version: 0.2.0
Summary: PySO8601 aims to parse any ISO 8601 date, including Week dates, Ordinal dates, intervals and durations.
Home-page: https://github.com/OldhamMade/PySO8601
Author: Phillip B Oldham
Author-email: phillip.oldham@gmail.com
License: UNKNOWN
Platform: UNKNOWN
